gtsam/__init__.py
gtsam/__init__.pyi
gtsam/gtsam.cpython-312-x86_64-linux-gnu.so
gtsam/gtsfm.py
gtsam/imuBias.py
gtsam/noiseModel.py
gtsam/symbol_shorthand.py
gtsam/Data/.gitignore
gtsam/Data/18pointExample1.txt
gtsam/Data/5pointExample1.txt
gtsam/Data/5pointExample2.txt
gtsam/Data/Balbianello.out
gtsam/Data/EqFdata.csv
gtsam/Data/HS21.QPS
gtsam/Data/HS268.QPS
gtsam/Data/HS35.QPS
gtsam/Data/HS35MOD.QPS
gtsam/Data/HS51.QPS
gtsam/Data/HS52.QPS
gtsam/Data/ISAM2_GT_city10000.txt
gtsam/Data/ISAM2_SmartFactorStereo_IMU.txt
gtsam/Data/KittiEquivBiasedImu.txt
gtsam/Data/KittiEquivBiasedImu_metadata.txt
gtsam/Data/KittiGps_converted.txt
gtsam/Data/Klaus3.g2o
gtsam/Data/Plaza1_.mat
gtsam/Data/Plaza1_DR.txt
gtsam/Data/Plaza1_TD.txt
gtsam/Data/Plaza2_.mat
gtsam/Data/Plaza2_DR.txt
gtsam/Data/Plaza2_TD.txt
gtsam/Data/QPExample.QPS
gtsam/Data/QPTEST.QPS
gtsam/Data/T1_city10000_04.txt
gtsam/Data/VO_calibration.txt
gtsam/Data/VO_calibration00.txt
gtsam/Data/VO_calibration00s.txt
gtsam/Data/VO_camera_poses00.txt
gtsam/Data/VO_camera_poses00s.txt
gtsam/Data/VO_camera_poses_large.txt
gtsam/Data/VO_stereo_factors00.txt
gtsam/Data/VO_stereo_factors00s.txt
gtsam/Data/VO_stereo_factors_large.txt
gtsam/Data/dubrovnik-1-1-pre.txt
gtsam/Data/dubrovnik-3-7-18-pre.txt
gtsam/Data/dubrovnik-3-7-pre.txt
gtsam/Data/example.graph
gtsam/Data/example_with_vertices.g2o
gtsam/Data/gazebo_ASV.csv
gtsam/Data/imuAndGPSdata.csv
gtsam/Data/issue1452.txt
gtsam/Data/noisyToyGraph.txt
gtsam/Data/optimizedNoisyToyGraph.txt
gtsam/Data/orientationsNoisyToyGraph.txt
gtsam/Data/pose2example.txt
gtsam/Data/pose3Localizationexample.txt
gtsam/Data/pose3example-grid.txt
gtsam/Data/pose3example-offdiagonal-rewritten.txt
gtsam/Data/pose3example-offdiagonal.txt
gtsam/Data/pose3example.txt
gtsam/Data/quadraped_imu_data.csv
gtsam/Data/randomGrid3D.xml
gtsam/Data/simpleGraph10gradIter.txt
gtsam/Data/sphere2500.txt
gtsam/Data/sphere2500_groundtruth.txt
gtsam_develop-4.3a1.dev202602010443.dist-info/METADATA
gtsam_develop-4.3a1.dev202602010443.dist-info/WHEEL
gtsam_develop-4.3a1.dev202602010443.dist-info/top_level.txt
gtsam_develop-4.3a1.dev202602010443.dist-info/RECORD
