Metadata-Version: 2.4
Name: gtsam-develop
Version: 4.3a1.dev202602010443
Summary: Georgia Tech Smoothing And Mapping library
Home-page: https://gtsam.org/
Author: Frank Dellaert et. al.
Author-email: frank.dellaert@gtsam.org
License: Simplified BSD license
Keywords: slam sam robotics localization mapping optimization
Classifier: Development Status :: 5 - Production/Stable
Classifier: Intended Audience :: Education
Classifier: Intended Audience :: Developers
Classifier: Intended Audience :: Science/Research
Classifier: Operating System :: MacOS
Classifier: Operating System :: Microsoft :: Windows
Classifier: Operating System :: POSIX
Classifier: License :: OSI Approved :: BSD License
Classifier: Programming Language :: Python :: 3
Requires-Dist: numpy>=1.11.0
Requires-Dist: pytest>=9.0.1
Dynamic: author
Dynamic: author-email
Dynamic: classifier
Dynamic: description
Dynamic: description-content-type
Dynamic: home-page
Dynamic: keywords
Dynamic: license
Dynamic: requires-dist
Dynamic: summary
